setup.py
cart2polar/__init__.py
cart2polar/cart2polar.py
cart2polar.egg-info/PKG-INFO
cart2polar.egg-info/SOURCES.txt
cart2polar.egg-info/dependency_links.txt
cart2polar.egg-info/not-zip-safe
cart2polar.egg-info/requires.txt
cart2polar.egg-info/top_level.txt