Metadata-Version: 1.0
Name: cart2polar
Version: 1.1
Summary: Cartesian to Polar Rebinning
Home-page: https://github.com/e-champenois/Polar-Rebinning
Author: Elio Champenois
Author-email: elio.champenois@gmail.com
License: MIT
Keywords: cart2polar,cartesian,polar,rebin,rebinning
Platform: UNKNOWN
